setup.py
punch/__init__.py
punch/app.py
punch.egg-info/PKG-INFO
punch.egg-info/SOURCES.txt
punch.egg-info/dependency_links.txt
punch.egg-info/requires.txt
punch.egg-info/top_level.txt