Metadata-Version: 1.1
Name: punch
Version: 0.0.1
Summary: A Python framework focused (but not limited) in JSON APIs.
Home-page: https://github.com/rochacon/punch
Author: Rodrigo Chacon
Author-email: rochacon@gmail.com
License: MIT
Keywords: Web,Python,Python3,Refactoring,REST,Framework,RPC
Platform: UNKNOWN
Classifier: Development Status :: 6 - Mature
Classifier: Intended Audience :: Developers
Classifier: Natural Language :: English
Classifier: Environment :: Console
Classifier: License :: OSI Approved :: MIT License
Classifier: Programming Language :: Python
Classifier: Programming Language :: Python :: 3
Classifier: Programming Language :: Python :: 3.2
Classifier: Programming Language :: Python :: 3.3
Classifier: Programming Language :: Python :: 3.4
Classifier: Programming Language :: Python :: 3.5
Classifier: Topic :: Software Development :: Libraries
Classifier: Topic :: Utilities
Requires: webob
